minenv/__init__.py
minenv/py.typed
minenv-0.1.0.dist-info/LICENSE
minenv-0.1.0.dist-info/METADATA
minenv-0.1.0.dist-info/WHEEL
minenv-0.1.0.dist-info/top_level.txt
minenv-0.1.0.dist-info/RECORD
