Metadata-Version: 2.2
Name: minenv
Version: 0.1.0
Summary: A minimal module for working with dotenv files.
Author-email: stefanlight8 <64615032+stefanlight8@users.noreply.github.com>
Project-URL: Repository, https://github.com/stefanlight8/minenv.git
Project-URL: Issues, https://github.com/stefanlight8/minenv/issues
Keywords: minimal,dotenv,env
Classifier: Intended Audience :: Developers
Classifier: License :: OSI Approved :: MIT License
Classifier: Programming Language :: Python :: 3.8
Classifier: Programming Language :: Python :: 3.9
Classifier: Programming Language :: Python :: 3.10
Classifier: Programming Language :: Python :: 3.11
Classifier: Programming Language :: Python :: 3.12
Classifier: Programming Language :: Python :: Implementation :: CPython
Classifier: Topic :: Utilities
Classifier: Typing :: Typed
Requires-Python: >=3.8
License-File: LICENSE
Provides-Extra: dev
Requires-Dist: pytest>=8.3.5; extra == "dev"
